schnetpack/__init__.py
schnetpack/cli.py
schnetpack/properties.py
schnetpack/task.py
schnetpack/units.py
schnetpack/atomistic/__init__.py
schnetpack/atomistic/aggregation.py
schnetpack/atomistic/atomwise.py
schnetpack/atomistic/distances.py
schnetpack/atomistic/electrostatic.py
schnetpack/atomistic/external_fields.py
schnetpack/atomistic/nuclear_repulsion.py
schnetpack/atomistic/response.py
schnetpack/configs/__init__.py
schnetpack/configs/predict.yaml
schnetpack/configs/train.yaml
schnetpack/configs/callbacks/checkpoint.yaml
schnetpack/configs/callbacks/earlystopping.yaml
schnetpack/configs/callbacks/ema.yaml
schnetpack/configs/callbacks/lrmonitor.yaml
schnetpack/configs/data/ani1.yaml
schnetpack/configs/data/custom.yaml
schnetpack/configs/data/iso17.yaml
schnetpack/configs/data/materials_project.yaml
schnetpack/configs/data/md17.yaml
schnetpack/configs/data/md22.yaml
schnetpack/configs/data/omdb.yaml
schnetpack/configs/data/qm9.yaml
schnetpack/configs/data/rmd17.yaml
schnetpack/configs/data/sampler/stratified_property.yaml
schnetpack/configs/experiment/md17.yaml
schnetpack/configs/experiment/qm9_atomwise.yaml
schnetpack/configs/experiment/qm9_dipole.yaml
schnetpack/configs/experiment/response.yaml
schnetpack/configs/experiment/rmd17.yaml
schnetpack/configs/globals/default_globals.yaml
schnetpack/configs/logger/aim.yaml
schnetpack/configs/logger/csv.yaml
schnetpack/configs/logger/tensorboard.yaml
schnetpack/configs/logger/wandb.yaml
schnetpack/configs/model/nnp.yaml
schnetpack/configs/model/representation/field_schnet.yaml
schnetpack/configs/model/representation/painn.yaml
schnetpack/configs/model/representation/schnet.yaml
schnetpack/configs/model/representation/so3net.yaml
schnetpack/configs/model/representation/radial_basis/bessel.yaml
schnetpack/configs/model/representation/radial_basis/gaussian.yaml
schnetpack/configs/run/default_run.yaml
schnetpack/configs/task/default_task.yaml
schnetpack/configs/task/optimizer/adabelief.yaml
schnetpack-2.1.1.dist-info/LICENSE
schnetpack-2.1.1.dist-info/METADATA
schnetpack-2.1.1.dist-info/WHEEL
schnetpack-2.1.1.dist-info/top_level.txt
schnetpack-2.1.1.dist-info/RECORD
