Metadata-Version: 2.1
Name: schnetpack
Version: 2.1.1
Summary: SchNetPack - Deep Neural Networks for Atomistic Systems
Author: Kristof T. Schuett, Michael Gastegger, Stefaan Hessmann, Niklas Gebauer, Jonas Lederer
License: COPYRIGHT
Requires-Python: >=3.10
License-File: LICENSE
Requires-Dist: numpy>=2.0.0
Requires-Dist: sympy<=1.12
Requires-Dist: ase>=3.21
Requires-Dist: h5py
Requires-Dist: pyyaml
Requires-Dist: hydra-core>=1.1.0
Requires-Dist: torch>=1.9
Requires-Dist: pytorch-lightning>=2.0.0
Requires-Dist: torchmetrics
Requires-Dist: hydra-colorlog>=1.1.0
Requires-Dist: rich
Requires-Dist: fasteners
Requires-Dist: dirsync
Requires-Dist: torch-ema
Requires-Dist: matscipy>=1.1.0
Requires-Dist: tensorboard>=2.17.1
Requires-Dist: tensorboardX>=2.6.2.2
Requires-Dist: tqdm
Requires-Dist: pre-commit
Requires-Dist: black
Requires-Dist: protobuf
Provides-Extra: test
Requires-Dist: pytest; extra == "test"
Requires-Dist: pytest-datadir; extra == "test"
Requires-Dist: pytest-benchmark; extra == "test"
